[{"model": "markets.productcategory", "pk": 1, "fields": {"name": "Menswear"}}, {"model": "markets.productcategory", "pk": 2, "fields": {"name": "Womenswear"}}, {"model": "markets.productcategory", "pk": 3, "fields": {"name": "Homewear"}}, {"model": "markets.productcategory", "pk": 4, "fields": {"name": "Childrenswear"}}, {"model": "markets.productcategory", "pk": 5, "fields": {"name": "Electronics"}}, {"model": "markets.productcategory", "pk": 6, "fields": {"name": "Health & Beauty"}}, {"model": "markets.productcategory", "pk": 7, "fields": {"name": "Sports Equipment"}}, {"model": "markets.productcategory", "pk": 8, "fields": {"name": "Giftware"}}, {"model": "markets.productcategory", "pk": 9, "fields": {"name": "Food & Drink"}}, {"model": "markets.productcategory", "pk": 10, "fields": {"name": "Media"}}, {"model": "markets.productcategory", "pk": 11, "fields": {"name": "Publishing"}}, {"model": "markets.productcategory", "pk": 12, "fields": {"name": "Marine"}}, {"model": "markets.productcategory", "pk": 13, "fields": {"name": "Automotive"}}, {"model": "markets.market", "pk": 1, "fields": {"name": "Amazon Japan", "description": "Amazon Japan", "web_address": "https://www.amazon.co.jp/", "country": "Japan", "region": "Asia", "product_category_demand": "", "size": "Huge", "product_category_size": "", "web_traffic_to_site": "Huge", "web_traffic_to_bounce": "Huge", "fee_pricing_structure": "Sandiego", "payment_terms": "Sandiego", "logistics_structure": "Sandiego", "seller_support_structure": "Sandiego", "translation_services": "Sandiego", "buyers_customer_service": "Sandiego", "merchandising_offer_cost": "Sandiego", "payment_methods": "Sandiego", "listing_languages": "", "product_visibility": "Sandiego", "competitor_comparison": "Sandiego", "ukti_terms": "Sandiego", "contact_details": "Sandiego", "shop_analytics": "Sandiego", "customization": "Sandiego", "feedback_system": "Sandiego", "product_categories": [8, 6, 3, 12, 10, 1, 11, 7]}}, {"model": "markets.market", "pk": 2, "fields": {"name": "Otto GmbH", "description": "Otto GmbH", "web_address": "https://www.otto.de/", "country": "Germany", "region": "European Union", "product_category_demand": "", "size": "Huge", "product_category_size": "", "web_traffic_to_site": "Huge", "web_traffic_to_bounce": "Huge", "fee_pricing_structure": "Sandiego", "payment_terms": "Sandiego", "logistics_structure": "Sandiego", "seller_support_structure": "Sandiego", "translation_services": "Sandiego", "buyers_customer_service": "Sandiego", "merchandising_offer_cost": "Sandiego", "payment_methods": "Sandiego", "listing_languages": "", "product_visibility": "Sandiego", "competitor_comparison": "Sandiego", "ukti_terms": "Sandiego", "contact_details": "Sandiego", "shop_analytics": "Sandiego", "customization": "Sandiego", "feedback_system": "Sandiego", "product_categories": [13, 5, 6]}}, {"model": "markets.market", "pk": 3, "fields": {"name": "Alibaba China", "description": "Alibaba China", "web_address": "https://www.alibaba.com/", "country": "China", "region": "Asia", "product_category_demand": "", "size": "Huge", "product_category_size": "", "web_traffic_to_site": "Huge", "web_traffic_to_bounce": "Huge", "fee_pricing_structure": "Sandiego", "payment_terms": "Sandiego", "logistics_structure": "Sandiego", "seller_support_structure": "Sandiego", "translation_services": "Sandiego", "buyers_customer_service": "Sandiego", "merchandising_offer_cost": "Sandiego", "payment_methods": "Sandiego", "listing_languages": "", "product_visibility": "Sandiego", "competitor_comparison": "Sandiego", "ukti_terms": "Sandiego", "contact_details": "Sandiego", "shop_analytics": "Sandiego", "customization": "Sandiego", "feedback_system": "Sandiego", "product_categories": [3, 1, 7]}}]